{
  "title": "Alampur Jogulamba Shakti Peetham: Chalukya Temples Guide",
  "slug": "alampur-jogulamba-temple-shakti-peetham",
  "excerpt": "Alampur Jogulamba Temple in Telangana is a must-visit destination famous for its Temples, Shakti Peetham, Chalukya and spectacular Deccani heritage. Read our expert travel blog to plan your perfect trip!",
  "featuredImage": "https://images.unsplash.com/photo-1628155930542-3c7a64e2c833?auto=format&fit=crop&w=1200&q=80",
  "content": "Welcome to the definitive travel chronicle of **Alampur Jogulamba Temple**, one of the most remarkable destinations nestled in the heart of the **Jogulamba Gadwal** district of Telangana. Dotted with spectacular cultural nuances, breathtaking geological landscapes, and an incredibly rich tapestry of history, Alampur Jogulamba Temple stands as an absolute jewel for both domestic and international travelers. Whether you are a dedicated history aficionado seeking medieval secrets, a spiritual pilgrim searching for divine solace, or an adventurous explorer yearning to conquer rugged Deccani terrains, this majestic location offers an experience that will leave you thoroughly spellbound. In this comprehensive guide, we delve deep into the historical legacy, top attractions, travel logistics, and local secrets of Alampur Jogulamba Temple to help you plan an unforgettable journey.\n\n### History and Cultural Legacy\n\nAlampur is recognized as the 'Dakshina Kashi' (Southern Varanasi) and is home to the fifth sacred Shakti Peetham, dedicated to Goddess Jogulamba. According to mythology, this is the spot where the upper teeth of Goddess Sati fell during Shiva's cosmic dance. The temple complex is also famous for the Navabrahma Temples - a spectacular cluster of nine stone temples dedicated to Lord Shiva, constructed in the 7th and 8th centuries AD by the Badami Chalukya rulers, showcasing the peak of ancient rock architecture.\n\nOver the centuries, the cultural matrix of Alampur Jogulamba Temple evolved as a beautiful synthesis of dynastic influences, classical Deccani folklore, and local artistic styles. This legacy is not merely preserved in books but stands tall in the towering stone monuments, pristine carvings, and active local festivals that continue to breathe life into the community. Visitors to this region can immediately feel the weight of this heritage, reflecting a golden era of military engineering, royal patronages, and artistic flourishing.\n\n### Architectural Grandeur & Top Attractions\n\nWhen you step into the scenic boundaries of Alampur Jogulamba Temple, you are greeted by an array of spectacular sights. Here are the top landmarks that must be on your itinerary:\n\n* **Goddess Jogulamba Shrine**: the ancient Shakti Peetham housing the powerful deity depicted in a unique posture.\n* **Navabrahma Temples**: a spectacular cluster of nine beautifully carved stone temples (Taraka, Bala, Swarga Brahma, etc.).\n* **Sangameswara Temple**: a historic Chola-era temple relocated stone-by-stone to prevent submergence in Srisailam reservoir.\n* **Tungabhadra Ghats**: scenic river steps leading into the sacred Tungabhadra River.\n* **Alampur Museum**: an archaeological museum displaying rare Chalukyan stone sculptures and inscriptions.\n\nEach of these architectural marvels tells a unique story of ancient engineering and creative genius, showcasing why this region remains at the absolute center of Telangana's tourism map.\n\n### Experiential Highlights & Things to Do\n\nTo truly immerse yourself in the magic of Alampur Jogulamba Temple, you must go beyond sightseeing and actively engage with the local experiences. Here are the top activities highly recommended by travel experts:\n\n1. **Pay respects at the highly sacred fifth Shakti Peetham of Goddess Jogulamba.**\n2. **Examine the detailed stone carvings on the outer walls of the Swarga Brahma and Bala Brahma temples.**\n3. **Take a holy bath at the wide concrete ghats of the Tungabhadra River.**\n4. **Browse the incredible collection of ancient stone idols at the Alampur Museum.**\n5. **Hire an expert guide to explain the Chalukyan architectural styles and inscription tablets.**\n\nParticipating in these unique activities guarantees that you experience the authentic pulse of the destination, creating lifelong memories.\n\n### Travel Logistics: Best Time to Visit & How to Reach\n\n* **Best Time to Visit**: The optimal window to plan your journey to Alampur Jogulamba Temple is during **October to March (Excellent weather for walking through the archaeological stone temples)**. The pleasant climate during this period makes long hours of outdoor exploration and sightseeing highly comfortable.\n\n* **How to Reach**: Getting to Alampur Jogulamba Temple is extremely convenient due to the state's modern, integrated transit infrastructure:\n  - ✈️ **By Air**: Rajiv Gandhi International Airport in Hyderabad (200 km). \n  - 🚂 **By Rail**: Alampur Road Railway Station (10 km) or Kurnool Station (15 km). \n  - 🚌 **By Road**: Located just off the Hyderabad-Bangalore Highway (NH44), easily reached via public buses running to Kurnool or Gadwal.\n\n### Local Deccani Flavors & Travel Tips\n\n* **Local Food Recommendations**: No travel experience is complete without indulging in the local culinary masterpieces. In this region, make sure to try **Relish spicy Rayalaseema-Telangana fusion meals (Ragi Sangati, fiery country chicken, spicy chutneys) available at traditional local diners.**. The rich blend of local spices and traditional cooking techniques creates a sensory explosion you cannot miss.\n\n* **Expert Travel Tips**: To ensure a smooth, hassle-free journey, keep these professional tips in mind:\n  - Wear comfortable cotton clothing, as the stone temples absorb heat\n  - Hire a guide to understand the unique architectural features of the nine different Brahma shrines.\n\n### Final Reflections\n\nAlampur Jogulamba Temple is more than just a pin on a tourist map; it is a living chronicle of Telangana's glorious Deccani heritage, natural brilliance, and spiritual depth. As you walk through its ancient archways, listen to the ambient whispers of history, and interact with the warm local community, you realize that the magic of this land lies in its ability to balance medieval grandeur with modern hospitality. Pack your bags, carry your camera, and set out to explore the wonders of Alampur Jogulamba Temple—a journey that promises to enrich your soul and redefine your love for travel.",
  "location": "Alampur Jogulamba Temple",
  "district": "Jogulamba Gadwal",
  "bestTimeToVisit": "October to March (Excellent weather for walking through the archaeological stone temples)",
  "history": "Alampur is recognized as the 'Dakshina Kashi' (Southern Varanasi) and is home to the fifth sacred Shakti Peetham, dedicated to Goddess Jogulamba. According to mythology, this is the spot where the upper teeth of Goddess Sati fell during Shiva's cosmic dance. The temple complex is also famous for the Navabrahma Temples - a spectacular cluster of nine stone temples dedicated to Lord Shiva, constructed in the 7th and 8th centuries AD by the Badami Chalukya rulers, showcasing the peak of ancient rock architecture.",
  "attractions": [
    "Goddess Jogulamba Shrine - the ancient Shakti Peetham housing the powerful deity depicted in a unique posture.",
    "Navabrahma Temples - a spectacular cluster of nine beautifully carved stone temples (Taraka, Bala, Swarga Brahma, etc.).",
    "Sangameswara Temple - a historic Chola-era temple relocated stone-by-stone to prevent submergence in Srisailam reservoir.",
    "Tungabhadra Ghats - scenic river steps leading into the sacred Tungabhadra River.",
    "Alampur Museum - an archaeological museum displaying rare Chalukyan stone sculptures and inscriptions."
  ],
  "thingsToDo": [
    "Pay respects at the highly sacred fifth Shakti Peetham of Goddess Jogulamba.",
    "Examine the detailed stone carvings on the outer walls of the Swarga Brahma and Bala Brahma temples.",
    "Take a holy bath at the wide concrete ghats of the Tungabhadra River.",
    "Browse the incredible collection of ancient stone idols at the Alampur Museum.",
    "Hire an expert guide to explain the Chalukyan architectural styles and inscription tablets."
  ],
  "howToReach": "Air: Rajiv Gandhi International Airport in Hyderabad (200 km). Rail: Alampur Road Railway Station (10 km) or Kurnool Station (15 km). Road: Located just off the Hyderabad-Bangalore Highway (NH44), easily reached via public buses running to Kurnool or Gadwal.",
  "nearbyPlaces": [
    "Kurnool Town (15 km) - historic gateway city in Andhra Pradesh.",
    "Jurala Dam (70 km) - major Krishna river dam.",
    "Gadwal Fort (60 km) - famous for heritage forts and handloom Gadwal sarees."
  ],
  "foodRecommendations": "Relish spicy Rayalaseema-Telangana fusion meals (Ragi Sangati, fiery country chicken, spicy chutneys) available at traditional local diners.",
  "travelTips": "Wear comfortable cotton clothing, as the stone temples absorb heat. Hire a guide to understand the unique architectural features of the nine different Brahma shrines.",
  "faqs": [
    {
      "q": "What is the significance of Alampur Jogulamba Temple?",
      "a": "It is highly significant as the fifth sacred Shakti Peetham among the 18 Maha Shakti Peethams, dedicated to Goddess Jogulamba."
    },
    {
      "q": "Who built the Navabrahma Temples in Alampur?",
      "a": "They were built in the 7th and 8th centuries AD by the Badami Chalukyas, representing early Chalukyan temple architecture."
    }
  ],
  "metaTitle": "Alampur Jogulamba Shakti Peetham: Chalukya Temples Guide",
  "metaDescription": "Explore Alampur Jogulamba Temple, the fifth sacred Shakti Peetham. Learn about the 7th-century Navabrahma Chalukya temples, museum, and river ghats.",
  "keywords": [
    "Alampur Jogulamba",
    "Shakti Peetham Alampur",
    "Navabrahma Temples",
    "Badami Chalukyas",
    "Tungabhadra River",
    "Dakshina Kashi"
  ],
  "category": "Temples",
  "tags": [
    "Temples",
    "Shakti Peetham",
    "Chalukya",
    "Heritage",
    "Tungabhadra"
  ],
  "publishedDate": "2026-05-29"
}