{
  "title": "Koilsagar Dam Mahabubnagar: Scenic Hills & Koilkonda Fort",
  "slug": "koilsagar-dam-and-reservoir",
  "excerpt": "Koilsagar Dam in Telangana is a must-visit destination famous for its Dams, Reservoirs, Scenic Hills and spectacular Deccani heritage. Read our expert travel blog to plan your perfect trip!",
  "featuredImage": "https://images.unsplash.com/photo-1580618672591-eb180b1a973f?auto=format&fit=crop&w=1200&q=80",
  "content": "Welcome to the definitive travel chronicle of **Koilsagar Dam**, one of the most remarkable destinations nestled in the heart of the **Mahabubnagar** district of Telangana. Dotted with spectacular cultural nuances, breathtaking geological landscapes, and an incredibly rich tapestry of history, Koilsagar Dam stands as an absolute jewel for both domestic and international travelers. Whether you are a dedicated history aficionado seeking medieval secrets, a spiritual pilgrim searching for divine solace, or an adventurous explorer yearning to conquer rugged Deccani terrains, this majestic location offers an experience that will leave you thoroughly spellbound. In this comprehensive guide, we delve deep into the historical legacy, top attractions, travel logistics, and local secrets of Koilsagar Dam to help you plan an unforgettable journey.\n\n### History and Cultural Legacy\n\nConstructed during the Nizam rule in the 1940s and completed in post-independence India, the Koilsagar Dam is built across the Peddavagu River (a tributary of the Krishna River). The dam is beautifully nestled between two high hills, creating a spectacular gorge-like reservoir. The project was designed to supply drinking water and irrigate the dry agricultural belts of Mahabubnagar, standing today as a highly popular weekend scenic spot.\n\nOver the centuries, the cultural matrix of Koilsagar Dam evolved as a beautiful synthesis of dynastic influences, classical Deccani folklore, and local artistic styles. This legacy is not merely preserved in books but stands tall in the towering stone monuments, pristine carvings, and active local festivals that continue to breathe life into the community. Visitors to this region can immediately feel the weight of this heritage, reflecting a golden era of military engineering, royal patronages, and artistic flourishing.\n\n### Architectural Grandeur & Top Attractions\n\nWhen you step into the scenic boundaries of Koilsagar Dam, you are greeted by an array of spectacular sights. Here are the top landmarks that must be on your itinerary:\n\n* **The Gorge Dam**: an elegant masonry dam structure nestled perfectly between two rocky hills.\n* **Koilsagar Reservoir**: vast, clean blue water body popular for sunset photography.\n* **Koilkonda Fort**: a majestic medieval hilltop fort located 15 km away, featuring high granite bastions.\n* **Veerabhadra Swamy Temple**: a beautiful ancient hilltop temple dedicated to Lord Shiva.\n* **Scenic Hill trekking**: multiple rugged trekking trails along the border hills.\n\nEach of these architectural marvels tells a unique story of ancient engineering and creative genius, showcasing why this region remains at the absolute center of Telangana's tourism map.\n\n### Experiential Highlights & Things to Do\n\nTo truly immerse yourself in the magic of Koilsagar Dam, you must go beyond sightseeing and actively engage with the local experiences. Here are the top activities highly recommended by travel experts:\n\n1. **Walk along the dam road to enjoy the spectacular view of the blue water framed by green hills.**\n2. **Trek up the rocky trails of the nearby Koilkonda Fort to explore its medieval gateways.**\n3. **Photograph the spectacular sunset reflecting in the massive reservoir basin.**\n4. **Visit the hilltop Veerabhadra Swamy Temple to seek blessings.**\n5. **Enjoy a quiet, scenic lakeside family picnic.**\n\nParticipating in these unique activities guarantees that you experience the authentic pulse of the destination, creating lifelong memories.\n\n### Travel Logistics: Best Time to Visit & How to Reach\n\n* **Best Time to Visit**: The optimal window to plan your journey to Koilsagar Dam is during **September to February (Post-monsoon when the reservoir is filled and surrounding hills are green)**. The pleasant climate during this period makes long hours of outdoor exploration and sightseeing highly comfortable.\n\n* **How to Reach**: Getting to Koilsagar Dam is extremely convenient due to the state's modern, integrated transit infrastructure:\n  - ✈️ **By Air**: Rajiv Gandhi International Airport in Hyderabad (130 km). \n  - 🚂 **By Rail**: Mahabubnagar Railway Station (38 km). \n  - 🚌 **By Road**: Easily reached by car via the Hyderabad-Mahabubnagar highway in about 2.5 hours.\n\n### Local Deccani Flavors & Travel Tips\n\n* **Local Food Recommendations**: No travel experience is complete without indulging in the local culinary masterpieces. In this region, make sure to try **Simple local Mahabubnagar vegetarian tiffins, fresh farm produce, hot mirchi bajji at local stalls, and standard meals at town hotels.**. The rich blend of local spices and traditional cooking techniques creates a sensory explosion you cannot miss.\n\n* **Expert Travel Tips**: To ensure a smooth, hassle-free journey, keep these professional tips in mind:\n  - Carry your own snacks and water, as there are limited commercial facilities at the dam site\n  - Dress comfortably for trekking if you plan to visit the Koilkonda Fort.\n\n### Final Reflections\n\nKoilsagar Dam is more than just a pin on a tourist map; it is a living chronicle of Telangana's glorious Deccani heritage, natural brilliance, and spiritual depth. As you walk through its ancient archways, listen to the ambient whispers of history, and interact with the warm local community, you realize that the magic of this land lies in its ability to balance medieval grandeur with modern hospitality. Pack your bags, carry your camera, and set out to explore the wonders of Koilsagar Dam—a journey that promises to enrich your soul and redefine your love for travel.",
  "location": "Koilsagar Dam",
  "district": "Mahabubnagar",
  "bestTimeToVisit": "September to February (Post-monsoon when the reservoir is filled and surrounding hills are green)",
  "history": "Constructed during the Nizam rule in the 1940s and completed in post-independence India, the Koilsagar Dam is built across the Peddavagu River (a tributary of the Krishna River). The dam is beautifully nestled between two high hills, creating a spectacular gorge-like reservoir. The project was designed to supply drinking water and irrigate the dry agricultural belts of Mahabubnagar, standing today as a highly popular weekend scenic spot.",
  "attractions": [
    "The Gorge Dam - an elegant masonry dam structure nestled perfectly between two rocky hills.",
    "Koilsagar Reservoir - vast, clean blue water body popular for sunset photography.",
    "Koilkonda Fort - a majestic medieval hilltop fort located 15 km away, featuring high granite bastions.",
    "Veerabhadra Swamy Temple - a beautiful ancient hilltop temple dedicated to Lord Shiva.",
    "Scenic Hill trekking - multiple rugged trekking trails along the border hills."
  ],
  "thingsToDo": [
    "Walk along the dam road to enjoy the spectacular view of the blue water framed by green hills.",
    "Trek up the rocky trails of the nearby Koilkonda Fort to explore its medieval gateways.",
    "Photograph the spectacular sunset reflecting in the massive reservoir basin.",
    "Visit the hilltop Veerabhadra Swamy Temple to seek blessings.",
    "Enjoy a quiet, scenic lakeside family picnic."
  ],
  "howToReach": "Air: Rajiv Gandhi International Airport in Hyderabad (130 km). Rail: Mahabubnagar Railway Station (38 km). Road: Easily reached by car via the Hyderabad-Mahabubnagar highway in about 2.5 hours.",
  "nearbyPlaces": [
    "Koilkonda Fort (15 km) - historic hilltop fortress ruins.",
    "Pillalamarri (35 km) - famous 800-year-old Banyan tree.",
    "Jurala Dam (45 km) - major Krishna river dam."
  ],
  "foodRecommendations": "Simple local Mahabubnagar vegetarian tiffins, fresh farm produce, hot mirchi bajji at local stalls, and standard meals at town hotels.",
  "travelTips": "Carry your own snacks and water, as there are limited commercial facilities at the dam site. Dress comfortably for trekking if you plan to visit the Koilkonda Fort.",
  "faqs": [
    {
      "q": "Is Koilsagar Dam built between two hills?",
      "a": "Yes, the unique feature of Koilsagar Dam is its construction in a narrow gorge between two high rocky hills."
    },
    {
      "q": "How far is Koilsagar from Hyderabad?",
      "a": "Koilsagar is located approximately 125 km southwest of Hyderabad and can be reached in about 2.5 hours."
    }
  ],
  "metaTitle": "Koilsagar Dam Mahabubnagar: Scenic Hills & Koilkonda Fort",
  "metaDescription": "Visit the scenic Koilsagar Dam in Mahabubnagar. Discover hilltop trekking trails, Koilkonda Fort ruins, temple visits, and travel directions.",
  "keywords": [
    "Koilsagar Dam",
    "Koilkonda Fort",
    "Mahabubnagar Tourism",
    "Telangana reservoirs",
    "Deccan trekking spots"
  ],
  "category": "Waterfalls",
  "tags": [
    "Dams",
    "Reservoirs",
    "Scenic Hills",
    "Spirituality",
    "Trekking"
  ],
  "publishedDate": "2026-05-29"
}